nginx2es/__init__.py
nginx2es/cli.py
nginx2es/nginx2es.py
nginx2es/parser.py
nginx2es/watcher.py
nginx2es-0.3.0.dist-info/DESCRIPTION.rst
nginx2es-0.3.0.dist-info/METADATA
nginx2es-0.3.0.dist-info/RECORD
nginx2es-0.3.0.dist-info/WHEEL
nginx2es-0.3.0.dist-info/entry_points.txt
nginx2es-0.3.0.dist-info/metadata.json
nginx2es-0.3.0.dist-info/pbr.json
nginx2es-0.3.0.dist-info/top_level.txt
