Metadata-Version: 2.0
Name: nginx2es
Version: 0.3.0
Summary: Put parsed Nginx access.log to Elasticsearch
Home-page: https://github.com/ei-grad/nginx2es
Author: Andrew Grigorev
Author-email: andrew@ei-grad.ru
License: MIT
Keywords: nginx access.log elasticsearch
Platform: UNKNOWN
Classifier: Development Status :: 4 - Beta
Classifier: Intended Audience :: System Administrators
Classifier: License :: OSI Approved :: MIT License
Classifier: Operating System :: Unix
Classifier: Topic :: Internet :: Log Analysis
Classifier: Topic :: System :: Logging
Classifier: Topic :: System :: Monitoring
Requires-Dist: elasticsearch
Requires-Dist: click
Requires-Dist: six
Requires-Dist: python-dateutil
Requires-Dist: inotify-simple
Requires-Dist: entrypoints
